aiomadeavr/__init__.py
aiomadeavr/__main__.py
aiomadeavr/avr.py
aiomadeavr/cli.py
aiomadeavr/discovery.py
aiomadeavr/enums.py
aiomadeavr/tui/__init__.py
aiomadeavr/tui/app.py
aiomadeavr/tui/widgets.py
aiomadeavr-1.1.1.dist-info/licenses/LICENSE
aiomadeavr-1.1.1.dist-info/METADATA
aiomadeavr-1.1.1.dist-info/WHEEL
aiomadeavr-1.1.1.dist-info/entry_points.txt
aiomadeavr-1.1.1.dist-info/top_level.txt
aiomadeavr-1.1.1.dist-info/RECORD
