Metadata-Version: 2.4
Name: aiomadeavr
Version: 1.1.1
Summary: Async library/utility to control Marantz/Denon AVR devices over telnet
Author-email: François Wautier <francois@wautier.eu>
License: MIT
Project-URL: Homepage, https://github.com/frawau/aiomadeavr
Project-URL: Repository, https://github.com/frawau/aiomadeavr
Project-URL: Issues, https://github.com/frawau/aiomadeavr/issues
Keywords: Marantz,Denon,AVR,Control,Network,asyncio
Classifier: Development Status :: 4 - Beta
Classifier: Intended Audience :: Developers
Classifier: License :: OSI Approved :: MIT License
Classifier: Operating System :: OS Independent
Classifier: Programming Language :: Python :: 3
Classifier: Programming Language :: Python :: 3.11
Classifier: Programming Language :: Python :: 3.12
Classifier: Programming Language :: Python :: 3.13
Classifier: Topic :: Home Automation
Classifier: Topic :: Multimedia :: Sound/Audio
Classifier: Framework :: AsyncIO
Requires-Python: >=3.11
License-File: LICENSE
Requires-Dist: aiohttp>=3.8.0
Provides-Extra: tui
Requires-Dist: textual>=0.50.0; extra == "tui"
Provides-Extra: dev
Requires-Dist: black; extra == "dev"
Requires-Dist: pytest; extra == "dev"
Requires-Dist: pytest-asyncio; extra == "dev"
Dynamic: license-file
